{
  "rows": [
    {
      "region_id": "01",
      "region_name": "Salawin",
      "value": 0.148582
    },
    {
      "region_id": "02",
      "region_name": "North Khong",
      "value": 0.0881
    },
    {
      "region_id": "03",
      "region_name": "Northeast Khong",
      "value": 0.138085
    },
    {
      "region_id": "04",
      "region_name": "Chi",
      "value": 0.160737
    },
    {
      "region_id": "05",
      "region_name": "Mun",
      "value": 0.124687
    },
    {
      "region_id": "06",
      "region_name": "Ping",
      "value": 0.123973
    },
    {
      "region_id": "07",
      "region_name": "Wang",
      "value": 0.110297
    },
    {
      "region_id": "08",
      "region_name": "Yom",
      "value": 0.111435
    },
    {
      "region_id": "09",
      "region_name": "Nan",
      "value": 0.103168
    },
    {
      "region_id": "10",
      "region_name": "Chao Phraya",
      "value": 0.149236
    },
    {
      "region_id": "10-is",
      "region_name": "Chao Phraya (Island)",
      "value": 0.125035
    },
    {
      "region_id": "11",
      "region_name": "Sakae Krang",
      "value": 0.1977
    },
    {
      "region_id": "12",
      "region_name": "Pasak",
      "value": 0.155688
    },
    {
      "region_id": "13",
      "region_name": "Tha Chin",
      "value": 0.216437
    },
    {
      "region_id": "14",
      "region_name": "Mae Klong",
      "value": 0.250929
    },
    {
      "region_id": "15",
      "region_name": "Bang Pakong",
      "value": 0.18003
    },
    {
      "region_id": "16",
      "region_name": "Tonle Sap",
      "value": 0.233572
    },
    {
      "region_id": "17",
      "region_name": "East Coast Gulf",
      "value": 0.168533
    },
    {
      "region_id": "17-is",
      "region_name": "East Coast Gulf (Island)",
      "value": 0.163139
    },
    {
      "region_id": "18",
      "region_name": "Phetchaburi - Prachuap Khiri Khan",
      "value": 0.303943
    },
    {
      "region_id": "18-is",
      "region_name": "Phetchaburi - Prachuap Khiri Khan (Island)",
      "value": 0.249945
    },
    {
      "region_id": "19",
      "region_name": "Peninsula - Upper East Coast",
      "value": 0.229366
    },
    {
      "region_id": "19-is",
      "region_name": "Peninsula - Upper East Coast (Island)",
      "value": 0.256739
    },
    {
      "region_id": "20",
      "region_name": "Thale Sap Songkhla",
      "value": 0.311757
    },
    {
      "region_id": "20-is",
      "region_name": "Thale Sap Songkhla (Island)",
      "value": null
    },
    {
      "region_id": "21",
      "region_name": "Peninsula - Lower East Coast",
      "value": 0.352585
    },
    {
      "region_id": "22",
      "region_name": "Peninsula - West Coast",
      "value": 0.280351
    },
    {
      "region_id": "22-is",
      "region_name": "Peninsula - West Coast (Island)",
      "value": 0.278567
    }
  ]
}