{
  "rows": [
    {
      "region_id": "0101",
      "region_name": "鹿茅脫谩脕猫禄脪脗碌脥鹿潞鹿",
      "value": 4.298827
    },
    {
      "region_id": "0102",
      "region_name": "脣茅脟脗谩脕猫脢脪",
      "value": -5.717421
    },
    {
      "region_id": "0103",
      "region_name": "鹿茅脫谩脕猫禄脪脗碌脥鹿脜猫脪搂脢猫脟鹿路脮猫 1",
      "value": 11.988418
    },
    {
      "region_id": "0104",
      "region_name": "鹿茅脫垄脥搂",
      "value": 30.83611
    },
    {
      "region_id": "0105",
      "region_name": "鹿茅脫谩脕猫禄脪脗碌脥鹿脜猫脪搂脢猫脟鹿路脮猫 2",
      "value": 26.324459
    },
    {
      "region_id": "0106",
      "region_name": "鹿茅脫谩脕猫脢脨脕脪麓",
      "value": 17.970813
    },
    {
      "region_id": "0107",
      "region_name": "鹿茅脫谩脕猫禄脪脗碌脥鹿脜猫脪搂脢猫脟鹿路脮猫 3",
      "value": 30.60797
    },
    {
      "region_id": "0108",
      "region_name": "鹿茅脫谩脕猫脢脴脙脭鹿路脙矛",
      "value": 17.628987
    },
    {
      "region_id": "0109",
      "region_name": "谩脕猫鹿茅脫脗脟脕碌脥鹿潞鹿",
      "value": 21.142274
    },
    {
      "region_id": "0110",
      "region_name": "鹿茅脫谩脕猫脜脪脣脜脟搂",
      "value": 23.610276
    },
    {
      "region_id": "0111",
      "region_name": "谩脕猫鹿茅脫脗脟脕碌脥鹿脜猫脪搂脢猫脟鹿路脮猫 1",
      "value": 27.494055
    },
    {
      "region_id": "0112",
      "region_name": "鹿茅脫谩脕猫脢脨脿脙脮脗搂",
      "value": 21.422617
    },
    {
      "region_id": "0113",
      "region_name": "谩脕猫鹿茅脫脗脟脕碌脥鹿脜猫脪搂脢猫脟鹿路脮猫 2",
      "value": 22.059748
    },
    {
      "region_id": "0114",
      "region_name": "鹿茅脫谩脕猫脙脭麓",
      "value": 6.486683
    },
    {
      "region_id": "0115",
      "region_name": "谩脕猫鹿茅脫脗脟脕碌脥鹿脜猫脪搂脢猫脟鹿路脮猫 3",
      "value": 11.003534
    },
    {
      "region_id": "0116",
      "region_name": "鹿茅脫谩脕猫脿搂脪",
      "value": 18.244054
    },
    {
      "region_id": "0117",
      "region_name": "谩脕猫鹿茅脫脗脟脕碌脥鹿脜猫脪搂脢猫脟鹿路脮猫 4",
      "value": 20.300078
    },
    {
      "region_id": "0118",
      "region_name": "谩脕猫鹿茅脫脢脪脜脨脟脭鹿碌脥鹿潞鹿",
      "value": 34.068415
    },
    {
      "region_id": "0119",
      "region_name": "鹿茅脫谩脕猫谩搂脨",
      "value": 33.996596
    },
    {
      "region_id": "0120",
      "region_name": "谩脕猫鹿茅脫脿脕脗碌脥鹿潞鹿",
      "value": 45.350409
    },
    {
      "region_id": "0121",
      "region_name": "脣茅脟脗谩脕猫脜脨脿脕脪",
      "value": 42.895669
    },
    {
      "region_id": "0122",
      "region_name": "谩脕猫鹿茅脫脿脕脗碌脥鹿脜猫脪搂",
      "value": 54.127809
    },
    {
      "region_id": "0201",
      "region_name": "谩脕猫鹿茅脫芒垄搂碌脥鹿潞鹿脢猫脟鹿路脮猫 1",
      "value": -29.77448
    },
    {
      "region_id": "0202",
      "region_name": "鹿茅脫谩脕猫篓脩鹿",
      "value": -33.227664
    },
    {
      "region_id": "0203",
      "region_name": "鹿茅脫谩脕猫陆脪搂",
      "value": -16.865524
    },
    {
      "region_id": "0204",
      "region_name": "鹿茅脫谩脕猫隆隆碌脥鹿脜猫脪搂脢猫脟鹿路脮猫 1",
      "value": -26.532587
    },
    {
      "region_id": "0205",
      "region_name": "鹿茅脫谩脕猫隆隆碌脥鹿脜猫脪搂脢猫脟鹿路脮猫 2",
      "value": -44.040367
    },
    {
      "region_id": "0206",
      "region_name": "鹿茅脫谩脕猫脜脪脟脢猫脟鹿路脮猫 1",
      "value": -16.22474
    },
    {
      "region_id": "0207",
      "region_name": "鹿茅脫谩脕猫脢脙脟脗",
      "value": -31.251561
    },
    {
      "region_id": "0208",
      "region_name": "鹿茅脫谩脕猫脜脪脟脢猫脟鹿路脮猫 2",
      "value": -37.703916
    },
    {
      "region_id": "0209",
      "region_name": "鹿茅脫谩脕猫隆隆碌脥鹿脜猫脪搂脢猫脟鹿路脮猫 3",
      "value": -45.572552
    },
    {
      "region_id": "0210",
      "region_name": "谩脕猫鹿茅脫芒垄搂碌脥鹿潞鹿脢猫脟鹿路脮猫 2",
      "value": -25.817719
    },
    {
      "region_id": "0211",
      "region_name": "谩脕猫鹿茅脫脥脭搂碌脥鹿潞鹿",
      "value": -5.996777
    },
    {
      "region_id": "0212",
      "region_name": "谩脕猫鹿茅脫脥脭搂碌脥鹿隆脜脪搂脢猫脟鹿路脮猫 1",
      "value": -1.528466
    },
    {
      "region_id": "0213",
      "region_name": "谩脕猫鹿茅脫戮脴搂",
      "value": -28.888091
    },
    {
      "region_id": "0214",
      "region_name": "谩脕猫鹿茅脫脥脭搂碌脥鹿隆脜脪搂脢猫脟鹿路脮猫 2",
      "value": -5.64015
    },
    {
      "region_id": "0215",
      "region_name": "谩脕猫脜脪脟",
      "value": -6.393626
    },
    {
      "region_id": "0216",
      "region_name": "谩脕猫鹿茅脫脥脭搂碌脥鹿脜猫脪搂",
      "value": -27.352909
    },
    {
      "region_id": "0217",
      "region_name": "谩脕猫鹿茅脫芒垄搂脢猫脟鹿路脮猫 2",
      "value": -27.737777
    },
    {
      "region_id": "0301",
      "region_name": "谩脕猫鹿茅脫芒垄搂脢猫脟鹿路脮猫 3",
      "value": 23.014037
    },
    {
      "region_id": "0302",
      "region_name": "鹿茅脫脣脕脩鹿",
      "value": 15.82413
    },
    {
      "region_id": "0303",
      "region_name": "鹿茅脫脢脪鹿",
      "value": 12.962561
    },
    {
      "region_id": "0304",
      "region_name": "谩脕猫鹿茅脫芒垄搂脢猫脟鹿路脮猫 4",
      "value": 20.7765
    },
    {
      "region_id": "0305",
      "region_name": "谩脕猫鹿茅脫脿脜脗碌脥鹿脜猫脪搂脢猫脟鹿路脮猫 1",
      "value": 16.346809
    },
    {
      "region_id": "0306",
      "region_name": "脣茅脟脗鹿茅脫禄脟鹿",
      "value": 22.996556
    },
    {
      "region_id": "0307",
      "region_name": "谩脕猫鹿茅脫脿脜脗碌脥鹿脜猫脪搂脢猫脟鹿路脮猫 2",
      "value": 22.973783
    },
    {
      "region_id": "0308",
      "region_name": "谩脕猫鹿茅脫芒垄搂脢猫脟鹿路脮猫 5",
      "value": 37.063403
    },
    {
      "region_id": "0309",
      "region_name": "脣茅脟脗鹿茅脫芒脢脕",
      "value": 31.430847
    },
    {
      "region_id": "0310",
      "region_name": "谩脕猫鹿茅脫芒垄搂脢猫脟鹿路脮猫 6/1",
      "value": 43.002349
    },
    {
      "region_id": "0311",
      "region_name": "鹿茅脫芒脕搂",
      "value": 24.469707
    },
    {
      "region_id": "0312",
      "region_name": "谩脕猫鹿茅脫芒垄搂脢猫脟鹿路脮猫 6/2",
      "value": 37.500712
    },
    {
      "region_id": "0313",
      "region_name": "鹿茅脫脢脟脗",
      "value": 44.376797
    },
    {
      "region_id": "0314",
      "region_name": "谩脕猫鹿茅脫芒垄搂脢猫脟鹿路脮猫 7/1",
      "value": 54.607438
    },
    {
      "region_id": "0315",
      "region_name": "脣茅脟脗脣脜脟搂脢猫脟鹿路脮猫 1",
      "value": 23.652405
    },
    {
      "region_id": "0316",
      "region_name": "脣茅脟脗麓脪鹿",
      "value": 37.95199
    },
    {
      "region_id": "0317",
      "region_name": "脣茅脟脗脣脜脟搂脢猫脟鹿路脮猫 2",
      "value": 54.714471
    },
    {
      "region_id": "0318",
      "region_name": "谩脕猫鹿茅脫芒垄搂脢猫脟鹿路脮猫 7/2",
      "value": 65.592975
    },
    {
      "region_id": "0319",
      "region_name": "谩脕猫鹿茅脫脢搂陇脙脪脕碌脥鹿潞鹿",
      "value": 49.559128
    },
    {
      "region_id": "0320",
      "region_name": "脣茅脟脗陇脥搂",
      "value": 63.061908
    },
    {
      "region_id": "0321",
      "region_name": "谩脕猫鹿茅脫脢搂陇脙脪脕碌脥鹿脜猫脪搂脢猫脟鹿路脮猫 1",
      "value": 55.955269
    },
    {
      "region_id": "0322",
      "region_name": "脣茅脟脗脦脮茅",
      "value": 63.939059
    },
    {
      "region_id": "0323",
      "region_name": "谩脕猫鹿茅脫脢搂陇脙脪脕碌脥鹿脜猫脪搂脢猫脟鹿路脮猫 2",
      "value": 64.322957
    },
    {
      "region_id": "0324",
      "region_name": "脣茅脟脗鹿茅脫脗脪脕",
      "value": 48.879885
    },
    {
      "region_id": "0325",
      "region_name": "谩脕猫鹿茅脫脢搂陇脙脪脕碌脥鹿脜猫脪搂脢猫脟鹿路脮猫 3",
      "value": 67.030618
    },
    {
      "region_id": "0326",
      "region_name": "脣茅脟脗鹿茅脫脥脵鹿",
      "value": 54.496347
    },
    {
      "region_id": "0327",
      "region_name": "谩脕猫鹿茅脫脢搂陇脙脪脕碌脥鹿脜猫脪搂脢猫脟鹿路脮猫 4",
      "value": 63.959927
    },
    {
      "region_id": "0328",
      "region_name": "脣茅脟脗路脟脗",
      "value": 47.372102
    },
    {
      "region_id": "0329",
      "region_name": "谩脕猫鹿茅脫芒垄搂脢猫脟鹿路脮猫 8",
      "value": 59.870283
    },
    {
      "region_id": "0330",
      "region_name": "鹿茅脫戮脴搂",
      "value": 47.953041
    },
    {
      "region_id": "0331",
      "region_name": "脣茅脟脗鹿茅脫隆猫脫",
      "value": 51.808751
    },
    {
      "region_id": "0332",
      "region_name": "谩脕猫鹿茅脫芒垄搂脢猫脟鹿路脮猫 9",
      "value": 47.394986
    },
    {
      "region_id": "0333",
      "region_name": "脣茅脟脗潞脪搂路脙脪脗",
      "value": 42.611225
    },
    {
      "region_id": "0334",
      "region_name": "脣茅脟脗脕脴隆",
      "value": 43.115216
    },
    {
      "region_id": "0335",
      "region_name": "脣茅脟脗潞脩搂脥脮茅",
      "value": 42.975918
    },
    {
      "region_id": "0336",
      "region_name": "谩脕猫鹿茅脫芒垄搂碌脥鹿脜猫脪搂",
      "value": 33.39989
    },
    {
      "region_id": "0401",
      "region_name": "脜脫鹿茅脫陋脮碌脥鹿潞鹿脢猫脟鹿路脮猫 1",
      "value": -2.400076
    },
    {
      "region_id": "0402",
      "region_name": "脜脫脢脨戮脴搂",
      "value": 1.239541
    },
    {
      "region_id": "0403",
      "region_name": "脜脫鹿茅脫陋脮碌脥鹿潞鹿脢猫脟鹿路脮猫 2",
      "value": 8.695578
    },
    {
      "region_id": "0404",
      "region_name": "脜脫隆脙脨篓脟鹿",
      "value": 10.681403
    },
    {
      "region_id": "0405",
      "region_name": "脜脫鹿茅脫陋脮脢猫脟鹿路脮猫 2/1",
      "value": 11.26088
    },
    {
      "region_id": "0406",
      "region_name": "脜脫陇脩鹿漏脵",
      "value": 13.26902
    },
    {
      "region_id": "0407",
      "region_name": "脜脫鹿茅脫陋脮脢猫脟鹿路脮猫 2/2",
      "value": 19.308405
    },
    {
      "region_id": "0408",
      "region_name": "脣茅脟脗脢脪脕脣脕脥",
      "value": 18.374203
    },
    {
      "region_id": "0409",
      "region_name": "脜脫鹿茅脫陋脮脢猫脟鹿路脮猫 3",
      "value": 27.807502
    },
    {
      "region_id": "0410",
      "region_name": "脜脫鹿茅脫戮脥搂碌脥鹿潞鹿脢猫脟鹿路脮猫 1",
      "value": 10.637541
    },
    {
      "region_id": "0411",
      "region_name": "鹿茅脫戮脟脗",
      "value": 18.845669
    },
    {
      "region_id": "0412",
      "region_name": "脜脫鹿茅脫戮脥搂碌脥鹿潞鹿脢猫脟鹿路脮猫 2",
      "value": 18.279921
    },
    {
      "region_id": "0413",
      "region_name": "脜脫戮脨脿鹿脮脗搂",
      "value": 20.649398
    },
    {
      "region_id": "0414",
      "region_name": "鹿茅脫戮脙脣脕",
      "value": 0.730152
    },
    {
      "region_id": "0415",
      "region_name": "脜脫鹿茅脫脿陋脭颅脢猫脟鹿路脮猫 1",
      "value": 2.179974
    },
    {
      "region_id": "0416",
      "region_name": "脜脫鹿茅脫脿陋脭颅脢猫脟鹿路脮猫 2",
      "value": 8.297205
    },
    {
      "region_id": "0417",
      "region_name": "脜脫鹿茅脫戮脥搂碌脥鹿潞鹿脢猫脟鹿路脮猫 3",
      "value": 18.304021
    },
    {
      "region_id": "0418",
      "region_name": "脜脫鹿茅脫戮脥搂碌脥鹿脜猫脪搂脢猫脟鹿路脮猫 1",
      "value": 25.591382
    },
    {
      "region_id": "0419",
      "region_name": "脣茅脟脗脢脪脗潞脪碌脙",
      "value": 38.034215
    },
    {
      "region_id": "0420",
      "region_name": "脜脫鹿茅脫戮脥搂碌脥鹿脜猫脪搂脢猫脟鹿路脮猫 2",
      "value": 35.289176
    },
    {
      "region_id": "0421",
      "region_name": "脜脫鹿茅脫陋脮脢猫脟鹿路脮猫 4/1",
      "value": 33.57697
    },
    {
      "region_id": "0422",
      "region_name": "脜脫禄脪脟碌脥鹿潞鹿",
      "value": 31.237379
    },
    {
      "region_id": "0423",
      "region_name": "脜脫戮脩鹿陋脪麓",
      "value": 51.419015
    },
    {
      "region_id": "0424",
      "region_name": "脜脫禄脪脟碌脥鹿脜猫脪搂",
      "value": 44.418371
    },
    {
      "region_id": "0425",
      "region_name": "脜脫鹿茅脫陋脮脢猫脟鹿路脮猫 4/2",
      "value": 33.778331
    },
    {
      "region_id": "0426",
      "region_name": "脜脫鹿茅脫脗脩搂",
      "value": 38.743025
    },
    {
      "region_id": "0427",
      "region_name": "脜脫鹿茅脫陋脮碌脥鹿脜猫脪搂",
      "value": 26.091279
    },
    {
      "region_id": "0501",
      "region_name": "脜脫鹿茅脫脕脵脜碌脥鹿潞鹿脢猫脟鹿路脮猫 1",
      "value": 32.256705
    },
    {
      "region_id": "0502",
      "region_name": "脜脫谩芦脨",
      "value": 18.922513
    },
    {
      "region_id": "0503",
      "region_name": "脜脫鹿茅脫脕脵脜碌脥鹿潞鹿脢猫脟鹿路脮猫 2",
      "value": 21.754893
    },
    {
      "region_id": "0504",
      "region_name": "脜脫戮脙脨脿戮脜脭搂",
      "value": 32.140156
    },
    {
      "region_id": "0505",
      "region_name": "脜脫鹿茅脫脕脵脜碌脥鹿潞鹿脢猫脟鹿路脮猫 3",
      "value": 26.430079
    },
    {
      "region_id": "0506",
      "region_name": "脜脫碌脨陇脥搂",
      "value": 21.48414
    },
    {
      "region_id": "0507",
      "region_name": "脜脫鹿茅脫脕脵脜碌脥鹿潞鹿脢猫脟鹿路脮猫 4",
      "value": 26.070495
    },
    {
      "region_id": "0508",
      "region_name": "脜脫脿陋脭搂盲隆脙",
      "value": 17.341995
    },
    {
      "region_id": "0509",
      "region_name": "脜脫篓脩隆脙脙脪陋",
      "value": 22.621742
    },
    {
      "region_id": "0510",
      "region_name": "脜脫鹿茅脫脕脵脜碌脥鹿潞鹿脢猫脟鹿路脮猫 5",
      "value": 28.652417
    },
    {
      "region_id": "0511",
      "region_name": "脜脫鹿脪搂脙脥搂",
      "value": 12.817748
    },
    {
      "region_id": "0512",
      "region_name": "脜脫禄脨脿路脮脗",
      "value": 14.944312
    },
    {
      "region_id": "0513",
      "region_name": "脜脫禄脜脪脗脕脪脠",
      "value": 16.918837
    },
    {
      "region_id": "0514",
      "region_name": "脜脫鹿茅脫脕脵脜脢猫脟鹿路脮猫 2/1",
      "value": 21.085732
    },
    {
      "region_id": "0515",
      "region_name": "脣茅脟脗脿脥隆",
      "value": 33.183362
    },
    {
      "region_id": "0516",
      "region_name": "脜脫脢脨谩路麓脢猫脟鹿路脮猫 1",
      "value": 23.94825
    },
    {
      "region_id": "0517",
      "region_name": "脜脫脢脨谩路麓脢猫脟鹿路脮猫 2",
      "value": 25.989066
    },
    {
      "region_id": "0518",
      "region_name": "脜脫鹿茅脫脕脵脜脢猫脟鹿路脮猫 2/2",
      "value": 17.639165
    },
    {
      "region_id": "0519",
      "region_name": "脜脫戮脩搂陋脵",
      "value": 24.819739
    },
    {
      "region_id": "0520",
      "region_name": "脜脫鹿茅脫脕脵脜脢猫脟鹿路脮猫 2/3",
      "value": 10.825744
    },
    {
      "region_id": "0521",
      "region_name": "脣茅脟脗碌脨芒陇搂",
      "value": 18.443997
    },
    {
      "region_id": "0522",
      "region_name": "脜脫鹿茅脫脕脵脜脢猫脟鹿路脮猫 2/4",
      "value": 11.463086
    },
    {
      "region_id": "0523",
      "region_name": "脜脫陋脮",
      "value": 14.692578
    },
    {
      "region_id": "0524",
      "region_name": "脜脫鹿茅脫脕脵脜脢猫脟鹿路脮猫 2/5",
      "value": 21.987932
    },
    {
      "region_id": "0525",
      "region_name": "脜脫戮脜脩潞戮脜脪",
      "value": 13.687588
    },
    {
      "region_id": "0526",
      "region_name": "脜脫鹿茅脫脕脵脜脢猫脟鹿路脮猫 2/6",
      "value": 27.724339
    },
    {
      "region_id": "0527",
      "region_name": "脜脫脿碌脪",
      "value": 15.248001
    },
    {
      "region_id": "0528",
      "region_name": "脜脫脿脢脮脗脟茫脣颅猫脢猫脟鹿路脮猫 1",
      "value": 23.058918
    },
    {
      "region_id": "0529",
      "region_name": "脜脫脿脢脮脗脟茫脣颅猫脢猫脟鹿路脮猫 2",
      "value": 17.960903
    },
    {
      "region_id": "0530",
      "region_name": "脜脫脿脢脮脗脟鹿茅脥脗",
      "value": 22.377358
    },
    {
      "region_id": "0531",
      "region_name": "脜脫脿脢脮脗脟茫脣颅猫脢猫脟鹿路脮猫 3",
      "value": 26.056864
    },
    {
      "region_id": "0532",
      "region_name": "脜脫鹿茅脫脕脵脜脢猫脟鹿路脮猫 2/7",
      "value": 31.815569
    },
    {
      "region_id": "0533",
      "region_name": "脣茅脟脗路脩潞路脩鹿",
      "value": 11.880535
    },
    {
      "region_id": "0534",
      "region_name": "脜脫鹿茅脫脕脵脜脢猫脟鹿路脮猫 3/1",
      "value": 28.70517
    },
    {
      "region_id": "0535",
      "region_name": "脣茅脟脗脢脫脙脪颅",
      "value": 6.451513
    },
    {
      "region_id": "0536",
      "region_name": "脜脫鹿茅脫脕脵脜脢猫脟鹿路脮猫 3/2",
      "value": 25.591932
    },
    {
      "region_id": "0537",
      "region_name": "脣茅脟脗路脪",
      "value": 2.708669
    },
    {
      "region_id": "0538",
      "region_name": "脣茅脟脗垄脗脴搂脢猫脟鹿路脮猫 1",
      "value": 1.338021
    },
    {
      "region_id": "0539",
      "region_name": "脣茅脟脗垄脗脴搂脢猫脟鹿路脮猫 2",
      "value": 21.095782
    },
    {
      "region_id": "0540",
      "region_name": "脜脫鹿茅脫脕脵脜脢猫脟鹿路脮猫 3/3",
      "value": 19.449557
    },
    {
      "region_id": "0541",
      "region_name": "脜脫鹿茅脫脕脵脜脢猫脟鹿路脮猫 3/4",
      "value": 22.866654
    },
    {
      "region_id": "0542",
      "region_name": "脜脫脿芦潞脪脗脢猫脟鹿路脮猫 1",
      "value": 37.416072
    },
    {
      "region_id": "0543",
      "region_name": "脣茅脟脗芒戮搂",
      "value": 36.37391
    },
    {
      "region_id": "0544",
      "region_name": "脜脫脿芦潞脪脗脢猫脟鹿路脮猫 2",
      "value": 30.436263
    },
    {
      "region_id": "0545",
      "region_name": "脜脫鹿茅脫脕脵脜脢猫脟鹿路脮猫 3/5",
      "value": 19.058062
    },
    {
      "region_id": "0546",
      "region_name": "脜脫脿芦潞隆",
      "value": 25.9527
    },
    {
      "region_id": "0547",
      "region_name": "脜脫鹿茅脫脕脵脜脢猫脟鹿路脮猫 3/6",
      "value": 16.140452
    },
    {
      "region_id": "0548",
      "region_name": "脜脫芒麓脕茫脣颅猫",
      "value": 18.804059
    },
    {
      "region_id": "0549",
      "region_name": "脜脫鹿茅脫脕脵脜碌脥鹿脜猫脪搂脢猫脟鹿路脮猫 1",
      "value": 21.354875
    },
    {
      "region_id": "0550",
      "region_name": "脣茅脟脗碌脴搂脜脴搂",
      "value": 27.685499
    },
    {
      "region_id": "0551",
      "region_name": "脜脫鹿茅脫脕脵脜碌脥鹿脜猫脪搂脢猫脟鹿路脮猫 2",
      "value": 26.780991
    },
    {
      "region_id": "0552",
      "region_name": "脜脫芒麓脕鹿茅脥脗",
      "value": 25.966434
    },
    {
      "region_id": "0553",
      "region_name": "脜脫鹿茅脫脕脵脜碌脥鹿脜猫脪搂脢猫脟鹿路脮猫 3",
      "value": 28.355008
    },
    {
      "region_id": "0601",
      "region_name": "谩脕猫鹿茅脫禄脭搂碌脥鹿潞鹿脢猫脟鹿路脮猫 1",
      "value": -6.173273
    },
    {
      "region_id": "0602",
      "region_name": "鹿茅脫谩脕猫搂脩麓",
      "value": -7.996494
    },
    {
      "region_id": "0603",
      "region_name": "谩脕猫鹿茅脫禄脭搂碌脥鹿潞鹿脢猫脟鹿路脮猫 2",
      "value": 1.457133
    },
    {
      "region_id": "0604",
      "region_name": "谩脕猫鹿茅脫谩脕猫谩碌搂",
      "value": -2.675803
    },
    {
      "region_id": "0605",
      "region_name": "谩脕猫鹿茅脫禄脭搂脢猫脟鹿路脮猫 2/1",
      "value": -0.254537
    },
    {
      "region_id": "0606",
      "region_name": "鹿茅脫谩脕猫脙脭脕",
      "value": -3.560516
    },
    {
      "region_id": "0607",
      "region_name": "谩脕猫鹿茅脫禄脭搂脢猫脟鹿路脮猫 2/2",
      "value": 12.90264
    },
    {
      "region_id": "0608",
      "region_name": "鹿茅脫谩脕猫隆脟搂",
      "value": 15.961787
    },
    {
      "region_id": "0609",
      "region_name": "谩脕猫鹿茅脫禄脭搂脢猫脟鹿路脮猫 2/3",
      "value": 18.645506
    },
    {
      "region_id": "0610",
      "region_name": "鹿茅脫谩脕猫垄脪鹿",
      "value": 2.87583
    },
    {
      "region_id": "0611",
      "region_name": "谩脕猫鹿茅脫禄脭搂脢猫脟鹿路脮猫 2/4",
      "value": 15.358185
    },
    {
      "region_id": "0612",
      "region_name": "鹿茅脫谩脕猫脜脮茅",
      "value": 25.473122
    },
    {
      "region_id": "0613",
      "region_name": "谩脕猫鹿茅脫禄脭搂脢猫脟鹿路脮猫 3/1",
      "value": 8.339747
    },
    {
      "region_id": "0614",
      "region_name": "鹿茅脫谩脕猫隆脜脪搂",
      "value": 9.84303
    },
    {
      "region_id": "0615",
      "region_name": "谩脕猫鹿茅脫禄脭搂脢猫脟鹿路脮猫 3/2",
      "value": 6.960547
    },
    {
      "region_id": "0616",
      "region_name": "鹿茅脫谩脕猫谩篓猫脕碌脥鹿潞鹿",
      "value": 8.347518
    },
    {
      "region_id": "0617",
      "region_name": "鹿茅脫谩脕猫谩篓猫脕碌脥鹿脜猫脪搂",
      "value": 14.445299
    },
    {
      "region_id": "0618",
      "region_name": "谩脕猫鹿茅脫禄脭搂脢猫脟鹿路脮猫 3/3",
      "value": 6.192502
    },
    {
      "region_id": "0619",
      "region_name": "谩脕猫鹿茅脫禄脭搂脢猫脟鹿路脮猫 3/4",
      "value": 22.008954
    },
    {
      "region_id": "0620",
      "region_name": "鹿茅脫谩脕猫碌脳猫鹿",
      "value": 33.97256
    },
    {
      "region_id": "0621",
      "region_name": "谩脕猫鹿茅脫禄脭搂脢猫脟鹿路脮猫 4/1",
      "value": 37.476092
    },
    {
      "region_id": "0622",
      "region_name": "谩脕猫鹿茅脫禄脭搂脢猫脟鹿路脮猫 4/2",
      "value": 36.96747
    },
    {
      "region_id": "0623",
      "region_name": "脣茅脟脗谩脕猫路茅脥",
      "value": 36.173038
    },
    {
      "region_id": "0624",
      "region_name": "谩脕猫鹿茅脫禄脭搂脢猫脟鹿路脮猫 4/3",
      "value": 35.683066
    },
    {
      "region_id": "0625",
      "region_name": "陇脜脥搂脟脩搂脿篓茅脪",
      "value": 35.027311
    },
    {
      "region_id": "0626",
      "region_name": "谩脕猫鹿茅脫禄脭搂脢猫脟鹿路脮猫 4/4",
      "value": 41.602553
    },
    {
      "region_id": "0627",
      "region_name": "陇脜脥搂谩脕猫脙脨隆脪",
      "value": 47.313273
    },
    {
      "region_id": "0628",
      "region_name": "谩脕猫鹿茅脫禄脭搂脢猫脟鹿路脮猫 4/5",
      "value": 41.511576
    },
    {
      "region_id": "0629",
      "region_name": "陇脜脥搂脢脟鹿脣脕脪隆",
      "value": 38.503801
    },
    {
      "region_id": "0630",
      "region_name": "谩脕猫鹿茅脫禄脭搂碌脥鹿脜猫脪搂",
      "value": 23.627417
    },
    {
      "region_id": "0701",
      "region_name": "谩脕猫鹿茅脫脟脩搂碌脥鹿潞鹿",
      "value": 3.807798
    },
    {
      "region_id": "0702",
      "region_name": "谩脕猫鹿茅脫脢脟脗",
      "value": 10.038168
    },
    {
      "region_id": "0703",
      "region_name": "谩脕猫鹿茅脫脟脩搂碌脥鹿隆脜脪搂脢猫脟鹿路脮猫 1",
      "value": 34.561203
    },
    {
      "region_id": "0704",
      "region_name": "鹿茅脫谩脕猫碌脴毛脗",
      "value": 23.259394
    },
    {
      "region_id": "0705",
      "region_name": "谩脕猫鹿茅脫脟脩搂碌脥鹿隆脜脪搂脢猫脟鹿路脮猫 2",
      "value": 26.497429
    },
    {
      "region_id": "0706",
      "region_name": "鹿茅脫谩脕猫篓脪搂",
      "value": 37.136721
    },
    {
      "region_id": "0707",
      "region_name": "谩脕猫鹿茅脫脟脩搂碌脥鹿脜猫脪搂脢猫脟鹿路脮猫 1",
      "value": 28.839534
    },
    {
      "region_id": "0708",
      "region_name": "鹿茅脫谩脕猫碌猫脫",
      "value": 31.784512
    },
    {
      "region_id": "0709",
      "region_name": "谩脕猫鹿茅脫脟脩搂碌脥鹿脜猫脪搂脢猫脟鹿路脮猫 2",
      "value": 33.545661
    },
    {
      "region_id": "0710",
      "region_name": "谩脕猫鹿茅脫脟脩搂碌脥鹿脜猫脪搂脢猫脟鹿路脮猫 3",
      "value": 29.558863
    },
    {
      "region_id": "0711",
      "region_name": "谩脕猫鹿茅脫脟脩搂碌脥鹿脜猫脪搂脢猫脟鹿路脮猫 4",
      "value": 41.617076
    },
    {
      "region_id": "0801",
      "region_name": "谩脕猫鹿茅脫脗脕碌脥鹿潞鹿脢猫脟鹿路脮猫 1",
      "value": -4.688132
    },
    {
      "region_id": "0802",
      "region_name": "谩脕猫鹿茅脫陇脟鹿",
      "value": -6.135852
    },
    {
      "region_id": "0803",
      "region_name": "谩脕猫鹿茅脫脗脕碌脥鹿潞鹿脢猫脟鹿路脮猫 2",
      "value": 2.584238
    },
    {
      "region_id": "0804",
      "region_name": "鹿茅脫禄脮茅",
      "value": 10.796375
    },
    {
      "region_id": "0805",
      "region_name": "谩脕猫鹿茅脫脗脕碌脥鹿潞鹿脢猫脟鹿路脮猫 3",
      "value": 16.022354
    },
    {
      "region_id": "0806",
      "region_name": "谩脕猫鹿茅脫搂脪脟",
      "value": 20.408558
    },
    {
      "region_id": "0807",
      "region_name": "谩脕猫鹿茅脫脗脕碌脥鹿隆脜脪搂脢猫脟鹿路脮猫 1",
      "value": 15.730065
    },
    {
      "region_id": "0808",
      "region_name": "鹿茅脫谩脕猫陇脫脕脮",
      "value": 10.785144
    },
    {
      "region_id": "0809",
      "region_name": "谩脕猫鹿茅脫脗脕碌脥鹿隆脜脪搂脢猫脟鹿路脮猫 2",
      "value": 34.632526
    },
    {
      "region_id": "0810",
      "region_name": "鹿茅脫谩脕猫碌茅脪",
      "value": 28.091814
    },
    {
      "region_id": "0811",
      "region_name": "谩脕猫鹿茅脫脗脕碌脥鹿脜猫脪搂脢猫脟鹿路脮猫 1",
      "value": 41.935106
    },
    {
      "region_id": "0812",
      "region_name": "脣茅脟脗谩脕猫脢脭鹿",
      "value": 52.230062
    },
    {
      "region_id": "0813",
      "region_name": "谩脕猫鹿茅脫脗脕碌脥鹿脜猫脪搂脢猫脟鹿路脮猫 2",
      "value": 49.286596
    },
    {
      "region_id": "0814",
      "region_name": "鹿茅脫谩脕猫脕脥隆",
      "value": 44.971017
    },
    {
      "region_id": "0815",
      "region_name": "谩脕猫鹿茅脫脗脕碌脥鹿脜猫脪搂脢猫脟鹿路脮猫 3",
      "value": 34.39835
    },
    {
      "region_id": "0816",
      "region_name": "鹿茅脫谩脕猫脙脫戮脩鹿",
      "value": 48.31489
    },
    {
      "region_id": "0817",
      "region_name": "谩脕猫鹿茅脫脗脕碌脥鹿脜猫脪搂脢猫脟鹿路脮猫 4",
      "value": 36.513113
    },
    {
      "region_id": "0818",
      "region_name": "陇脜脥搂潞脪搂谩隆茅脟",
      "value": 24.333536
    },
    {
      "region_id": "0819",
      "region_name": "谩脕猫鹿茅脫脗脕碌脥鹿脜猫脪搂脢猫脟鹿路脮猫 5",
      "value": 7.07654
    },
    {
      "region_id": "0901",
      "region_name": "谩脕猫鹿茅脫鹿猫脪鹿碌脥鹿潞鹿",
      "value": -9.616665
    },
    {
      "region_id": "0902",
      "region_name": "脣茅脟脗鹿茅脫脗脪脟 (1)",
      "value": -11.248246
    },
    {
      "region_id": "0903",
      "region_name": "谩脕猫鹿茅脫鹿猫脪鹿脢猫脟鹿路脮猫 2/1",
      "value": 0.048355
    },
    {
      "region_id": "0904",
      "region_name": "鹿茅脫脗脪脟 (2)",
      "value": -2.974477
    },
    {
      "region_id": "0905",
      "region_name": "谩脕猫鹿茅脫鹿猫脪鹿脢猫脟鹿路脮猫 2/2",
      "value": -1.695383
    },
    {
      "region_id": "0906",
      "region_name": "鹿茅脫脢脕脴鹿",
      "value": 1.276756
    },
    {
      "region_id": "0907",
      "region_name": "谩脕猫鹿茅脫鹿猫脪鹿脢猫脟鹿路脮猫 2/3",
      "value": 3.728654
    },
    {
      "region_id": "0908",
      "region_name": "鹿茅脫脢脪",
      "value": 11.44763
    },
    {
      "region_id": "0909",
      "region_name": "谩脕猫鹿茅脫鹿猫脪鹿脢猫脟鹿路脮猫 2/4",
      "value": 4.071061
    },
    {
      "region_id": "0910",
      "region_name": "鹿茅脫脟茅脪",
      "value": 2.05128
    },
    {
      "region_id": "0911",
      "region_name": "谩脕猫鹿茅脫鹿猫脪鹿脢猫脟鹿路脮猫 3/1",
      "value": 7.266439
    },
    {
      "region_id": "0912",
      "region_name": "鹿茅脫谩脣搂",
      "value": 18.078649
    },
    {
      "region_id": "0913",
      "region_name": "谩脕猫鹿茅脫鹿猫脪鹿脢猫脟鹿路脮猫 3/2",
      "value": 32.125115
    },
    {
      "region_id": "0914",
      "region_name": "鹿茅脫禄脪麓",
      "value": 30.571393
    },
    {
      "region_id": "0915",
      "region_name": "谩脕猫鹿茅脫鹿猫脪鹿脢猫脟鹿路脮猫 4/1",
      "value": 52.224309
    },
    {
      "region_id": "0916",
      "region_name": "陇脜脥搂碌脙脥鹿",
      "value": 39.698152
    },
    {
      "region_id": "0917",
      "region_name": "谩脕猫鹿茅脫鹿猫脪鹿脢猫脟鹿路脮猫 4/2",
      "value": 41.943133
    },
    {
      "region_id": "0918",
      "region_name": "谩脕猫鹿茅脫谩陇脟鹿茅脥脗脢猫脟鹿路脮猫 1",
      "value": 9.382228
    },
    {
      "region_id": "0919",
      "region_name": "鹿茅脫脌脪陇",
      "value": 25.222082
    },
    {
      "region_id": "0920",
      "region_name": "谩脕猫鹿茅脫谩陇脟鹿茅脥脗脢猫脟鹿路脮猫 2",
      "value": 21.00216
    },
    {
      "region_id": "0921",
      "region_name": "谩脕猫鹿茅脫鹿猫脪鹿碌脥鹿脜猫脪搂脢猫脟鹿路脮猫 1",
      "value": 12.986287
    },
    {
      "region_id": "0922",
      "region_name": "谩脕猫鹿茅脫脟脩搂路脥搂",
      "value": 4.065695
    },
    {
      "region_id": "0923",
      "region_name": "谩脕猫鹿茅脫鹿猫脪鹿碌脥鹿脜猫脪搂脢猫脟鹿路脮猫 2",
      "value": -0.536115
    },
    {
      "region_id": "1001",
      "region_name": "潞脰搂潞脙脿戮莽麓",
      "value": 2.789824
    },
    {
      "region_id": "1002",
      "region_name": "路脮猫脙脪潞谩脕猫鹿茅脫脿篓茅脪戮脙脨脗脪",
      "value": 12.000752
    },
    {
      "region_id": "1101",
      "region_name": "鹿茅脫谩脕猫脟搂",
      "value": 29.73598
    },
    {
      "region_id": "1102",
      "region_name": "谩脕猫鹿茅脫脢脨谩隆隆脙脩搂碌脥鹿脜猫脪搂脢猫脟鹿路脮猫 1",
      "value": 17.584596
    },
    {
      "region_id": "1103",
      "region_name": "陇脜脥搂芒戮赂脭矛",
      "value": 16.864727
    },
    {
      "region_id": "1104",
      "region_name": "脣茅脟脗路脩潞脿脢脜脪",
      "value": 20.50806
    },
    {
      "region_id": "1105",
      "region_name": "谩脕猫鹿茅脫脢脨谩隆隆脙脩搂碌脥鹿脜猫脪搂脢猫脟鹿路脮猫 2",
      "value": 16.326927
    },
    {
      "region_id": "1106",
      "region_name": "谩脕猫鹿茅脫脢脨谩隆隆脙脩搂碌脥鹿脜猫脪搂脢猫脟鹿路脮猫 3",
      "value": 14.227563
    },
    {
      "region_id": "1201",
      "region_name": "谩脕猫鹿茅脫禄猫脪脢脩隆碌脥鹿潞鹿",
      "value": 9.746103
    },
    {
      "region_id": "1202",
      "region_name": "脣茅脟脗鹿茅脫戮脴搂",
      "value": -2.73496
    },
    {
      "region_id": "1203",
      "region_name": "谩脕猫鹿茅脫禄猫脪脢脩隆脢猫脟鹿路脮猫 2",
      "value": -0.627621
    },
    {
      "region_id": "1204",
      "region_name": "陇脜脥搂脣茅脟脗潞猫脥",
      "value": 3.069527
    },
    {
      "region_id": "1205",
      "region_name": "谩脕猫鹿茅脫禄猫脪脢脩隆脢猫脟鹿路脮猫 3/1",
      "value": 6.982626
    },
    {
      "region_id": "1206",
      "region_name": "脣茅脟脗脿隆脪脨谩隆茅脟",
      "value": 14.934902
    },
    {
      "region_id": "1207",
      "region_name": "谩脕猫鹿茅脫禄猫脪脢脩隆脢猫脟鹿路脮猫 3/2",
      "value": 13.660343
    },
    {
      "region_id": "1208",
      "region_name": "脜脫脢鹿赂脭",
      "value": 16.899612
    },
    {
      "region_id": "1209",
      "region_name": "谩脕猫鹿茅脫禄猫脪脢脩隆碌脥鹿脜猫脪搂脢猫脟鹿路脮猫 1",
      "value": 12.752918
    },
    {
      "region_id": "1210",
      "region_name": "脣茅脟脗脣脕脟隆脿脣脜莽隆",
      "value": 19.380978
    },
    {
      "region_id": "1211",
      "region_name": "谩脕猫鹿茅脫禄猫脪脢脩隆碌脥鹿脜猫脪搂脢猫脟鹿路脮猫 2",
      "value": 27.390309
    },
    {
      "region_id": "1301",
      "region_name": "脣茅脟脗隆脙脨脿脢脮脗脟",
      "value": 21.600964
    },
    {
      "region_id": "1302",
      "region_name": "路脮猫脙脪潞谩脕猫鹿茅脫路猫脪篓脮鹿",
      "value": 14.369991
    },
    {
      "region_id": "1401",
      "region_name": "谩脕猫鹿茅脫谩陇脟茫脣颅猫碌脥鹿潞鹿脢猫脟鹿路脮猫 1",
      "value": 48.928353
    },
    {
      "region_id": "1402",
      "region_name": "脣茅脟脗谩脕猫脜脨脕脴搂",
      "value": 38.836496
    },
    {
      "region_id": "1403",
      "region_name": "谩脕猫鹿茅脫谩陇脟茫脣颅猫碌脥鹿潞鹿脢猫脟鹿路脮猫 2",
      "value": 43.629407
    },
    {
      "region_id": "1404",
      "region_name": "脣茅脟脗谩脕猫篓脩鹿",
      "value": 62.07942
    },
    {
      "region_id": "1405",
      "region_name": "谩脕猫鹿茅脫谩陇脟茫脣颅猫碌脥鹿潞鹿脢猫脟鹿路脮猫 3",
      "value": 51.089186
    },
    {
      "region_id": "1406",
      "region_name": "脣茅脟脗垄脪谩垄茅搂",
      "value": 30.026518
    },
    {
      "region_id": "1407",
      "region_name": "谩脕猫鹿茅脫谩陇脟茫脣颅猫碌脥鹿脜猫脪搂脢猫脟鹿路脮猫 1",
      "value": 39.182641
    },
    {
      "region_id": "1408",
      "region_name": "脣茅脟脗碌脨脿戮脭鹿",
      "value": 20.977377
    },
    {
      "region_id": "1409",
      "region_name": "谩脕猫鹿茅脫谩陇脟茫脣颅猫碌脥鹿脜猫脪搂脢猫脟鹿路脮猫 2",
      "value": 21.494624
    },
    {
      "region_id": "1410",
      "region_name": "谩脕猫鹿茅脫谩陇脟鹿茅脥脗碌脥鹿潞鹿脢猫脟鹿路脮猫 1",
      "value": 91.972765
    },
    {
      "region_id": "1411",
      "region_name": "脣茅脟脗禄脭脜脥隆",
      "value": 82.951143
    },
    {
      "region_id": "1412",
      "region_name": "谩脕猫鹿茅脫谩陇脟鹿茅脥脗碌脥鹿潞鹿脢猫脟鹿路脮猫 2",
      "value": 56.551282
    },
    {
      "region_id": "1413",
      "region_name": "谩脕猫鹿茅脫谩陇脟鹿茅脥脗碌脥鹿脜猫脪搂脢猫脟鹿路脮猫 1",
      "value": 73.952827
    },
    {
      "region_id": "1414",
      "region_name": "谩脕猫鹿茅脫谩陇脟鹿茅脥脗碌脥鹿脜猫脪搂脢猫脟鹿路脮猫 2",
      "value": 35.62377
    },
    {
      "region_id": "1415",
      "region_name": "脜脫脌脪陋脮",
      "value": 17.716838
    },
    {
      "region_id": "1416",
      "region_name": "谩脕猫鹿茅脫谩陇脟鹿茅脥脗碌脥鹿脜猫脪搂脢猫脟鹿路脮猫 3",
      "value": 18.940058
    },
    {
      "region_id": "1417",
      "region_name": "路脮猫脙脪潞谩脕猫鹿茅脫谩脕猫隆脜脥搂",
      "value": 15.300631
    },
    {
      "region_id": "1501",
      "region_name": "陇脜脥搂戮脙脨脢路脰搂",
      "value": 14.168571
    },
    {
      "region_id": "1502",
      "region_name": "谩脕猫鹿茅脫戮脙脨禄脙搂脢猫脟鹿路脮猫 1",
      "value": 33.840902
    },
    {
      "region_id": "1503",
      "region_name": "谩脕猫鹿茅脫戮脙脨禄脙搂脢猫脟鹿路脮猫 2",
      "value": 42.852976
    },
    {
      "region_id": "1504",
      "region_name": "谩脕猫鹿茅脫脣鹿脴脕脪鹿",
      "value": 63.730089
    },
    {
      "region_id": "1505",
      "region_name": "谩脕猫鹿茅脫禄脙脪篓脮鹿潞脴脙脮碌脥鹿脜猫脪搂",
      "value": 59.541848
    },
    {
      "region_id": "1506",
      "region_name": "谩脕猫鹿茅脫鹿陇脙鹿脪脗隆",
      "value": 35.500611
    },
    {
      "region_id": "1507",
      "region_name": "路脮猫脙脪潞谩脕猫鹿茅脫潞脪搂禄脨隆搂脢猫脟鹿路脮猫 1",
      "value": 17.566355
    },
    {
      "region_id": "1508",
      "region_name": "陇脜脥搂路猫脪脜脪麓",
      "value": 27.685785
    },
    {
      "region_id": "1509",
      "region_name": "陇脜脥搂脣脜脟搂",
      "value": 10.323621
    },
    {
      "region_id": "1510",
      "region_name": "路脮猫脙脪潞谩脕猫鹿茅脫潞脪搂禄脨隆搂脢猫脟鹿路脮猫 2",
      "value": 12.441358
    },
    {
      "region_id": "1601",
      "region_name": "芒碌鹿脿脜脢脪禄碌脥鹿潞鹿 (脜脴猫脕鹿茅脫脢脪垄脪)",
      "value": 27.502142
    },
    {
      "region_id": "1602",
      "region_name": "脣茅脟脗戮脙脕芒脣麓",
      "value": 30.491748
    },
    {
      "region_id": "1603",
      "region_name": "芒碌鹿脿脜脢脪禄碌脥鹿脜猫脪搂",
      "value": 9.27131
    },
    {
      "region_id": "1701",
      "region_name": "陋脪脗陆脩猫搂路脨脿脜碌脨脟脩鹿脥脥隆 (脜脴猫脕鹿茅脫脢脪垄脪 1)",
      "value": 11.716457
    },
    {
      "region_id": "1702",
      "region_name": "陇脜脥搂茫脣颅猫",
      "value": 16.917824
    },
    {
      "region_id": "1703",
      "region_name": "陋脪脗陆脩猫搂路脨脿脜碌脨脟脩鹿脥脥隆 (脜脴猫脕鹿茅脫脢脪垄脪 2)",
      "value": 14.767104
    },
    {
      "region_id": "1704",
      "region_name": "谩脕猫鹿茅脫禄脙脨谩脢",
      "value": 8.014411
    },
    {
      "region_id": "1705",
      "region_name": "陋脪脗陆脩猫搂路脨脿脜碌脨脟脩鹿脥脥隆 (脜脴猫脕鹿茅脫脢脪垄脪 3)",
      "value": -11.157649
    },
    {
      "region_id": "1706",
      "region_name": "陇脜脥搂芒碌鹿麓",
      "value": -5.456059
    },
    {
      "region_id": "1707",
      "region_name": "谩脕猫鹿茅脫篓脩鹿路潞脴脙脮",
      "value": 2.300059
    },
    {
      "region_id": "1708",
      "region_name": "陋脪脗陆脩猫搂路脨脿脜碌脨脟脩鹿脥脥隆 (脜脴猫脕鹿茅脫脢脪垄脪 4)",
      "value": 21.653207
    },
    {
      "region_id": "1709",
      "region_name": "谩脕猫鹿茅脫脿脕脳脥搂碌脙脪麓",
      "value": 23.056895
    },
    {
      "region_id": "1710",
      "region_name": "陋脪脗陆脩猫搂路脨脿脜碌脨脟脩鹿脥脥隆 (脜脴猫脕鹿茅脫脢脪垄脪 5)",
      "value": 26.754878
    },
    {
      "region_id": "1801",
      "region_name": "谩脕猫鹿茅脫脿戮陋脙潞脴脙脮碌脥鹿潞鹿",
      "value": 3.891307
    },
    {
      "region_id": "1802",
      "region_name": "脣茅脟脗谩脕猫禄脙脨篓脩鹿",
      "value": -1.294616
    },
    {
      "region_id": "1803",
      "region_name": "谩脕猫鹿茅脫脿戮陋脙潞脴脙脮碌脥鹿脜猫脪搂",
      "value": 2.496934
    },
    {
      "region_id": "1804",
      "region_name": "谩脕猫鹿茅脫禄脙脪鲁潞脴脙脮 ( 脜脴猫脕鹿茅脫脢脪垄脪 )",
      "value": 5.716627
    },
    {
      "region_id": "1805",
      "region_name": "陇脜脥搂脿垄脪谩麓搂",
      "value": 2.973993
    },
    {
      "region_id": "1806",
      "region_name": "陇脜脥搂隆脴脗",
      "value": 7.534592
    },
    {
      "region_id": "1807",
      "region_name": "陋脪脗陆脩猫搂路脨脿脜禄脙脨篓脟潞陇脮脙脮垄脩鹿赂矛脢猫脟鹿路脮猫 1",
      "value": 11.84318
    },
    {
      "region_id": "1808",
      "region_name": "陇脜脥搂潞脪搂脢脨戮脪鹿茫脣颅猫",
      "value": 21.77913
    },
    {
      "region_id": "1809",
      "region_name": "陋脪脗陆脩猫搂路脨脿脜禄脙脨篓脟潞陇脮脙脮垄脩鹿赂矛脢猫脟鹿路脮猫 2",
      "value": 19.413628
    },
    {
      "region_id": "1901",
      "region_name": "脌脪陇茫碌茅陆脩猫搂碌脨脟脩鹿脥脥隆碌脥鹿潞鹿脢猫脟鹿路脮猫 1",
      "value": 28.453348
    },
    {
      "region_id": "1902",
      "region_name": "陇脜脥搂路猫脪碌脨脿脌脪 ( 脜脴猫脕鹿茅脫脢脪垄脪 )",
      "value": 44.1931
    },
    {
      "region_id": "1903",
      "region_name": "脌脪陇茫碌茅陆脩猫搂碌脨脟脩鹿脥脥隆碌脥鹿潞鹿脢猫脟鹿路脮猫 2",
      "value": 41.186232
    },
    {
      "region_id": "1904",
      "region_name": "陇脜脥搂脣脜脩搂脢脟鹿",
      "value": 88.89889
    },
    {
      "region_id": "1905",
      "region_name": "脌脪陇茫碌茅陆脩猫搂碌脨脟脩鹿脥脥隆脢猫脟鹿路脮猫 2",
      "value": 28.213547
    },
    {
      "region_id": "1906",
      "region_name": "陇脜脥搂脢隆",
      "value": 106.809331
    },
    {
      "region_id": "1907",
      "region_name": "陇脜脥搂戮脙脨谩脢搂",
      "value": 131.72572
    },
    {
      "region_id": "1908",
      "region_name": "陇脜脥搂戮脴脕麓脟搂碌脥鹿脜猫脪搂",
      "value": 57.226366
    },
    {
      "region_id": "1909",
      "region_name": "陇脜脥搂篓脩鹿麓脮",
      "value": 32.843242
    },
    {
      "region_id": "1910",
      "region_name": "谩脕猫鹿茅脫碌脪禄脮碌脥鹿潞鹿脢猫脟鹿路脮猫 1",
      "value": 24.856844
    },
    {
      "region_id": "1911",
      "region_name": "谩脕猫鹿茅脫碌脪禄脮碌脥鹿潞鹿脢猫脟鹿路脮猫 2",
      "value": 29.034676
    },
    {
      "region_id": "1912",
      "region_name": "陇脜脥搂脢脭鹿禄脴鹿",
      "value": 38.520673
    },
    {
      "region_id": "1913",
      "region_name": "谩脕猫鹿茅脫碌脪禄脮碌脥鹿脜猫脪搂脢猫脟鹿路脮猫 1",
      "value": 24.321785
    },
    {
      "region_id": "1914",
      "region_name": "陇脜脥搂脥脭禄脩鹿",
      "value": 45.960751
    },
    {
      "region_id": "1915",
      "region_name": "谩脕猫鹿茅脫碌脪禄脮碌脥鹿脜猫脪搂脢猫脟鹿路脮猫 2",
      "value": 23.958172
    },
    {
      "region_id": "1916",
      "region_name": "谩脕猫鹿茅脫碌脪禄脮碌脥鹿脜猫脪搂脢猫脟鹿路脮猫 3",
      "value": 22.208114
    },
    {
      "region_id": "1917",
      "region_name": "脌脪陇茫碌茅陆脩猫搂碌脨脟脩鹿脥脥隆脢猫脟鹿路脮猫 3",
      "value": 16.103531
    },
    {
      "region_id": "1918",
      "region_name": "陇脜脥搂隆脜脪脗",
      "value": 22.963222
    },
    {
      "region_id": "1919",
      "region_name": "脌脪陇茫碌茅陆脩猫搂碌脨脟脩鹿脥脥隆脢猫脟鹿路脮猫 4",
      "value": 20.331791
    },
    {
      "region_id": "2001",
      "region_name": "路脨脿脜鹿茅脥脗",
      "value": 18.990741
    },
    {
      "region_id": "2002",
      "region_name": "路脨脿脜脣脜脟搂",
      "value": 18.105023
    },
    {
      "region_id": "2003",
      "region_name": "路脨脿脜脢脪潞脢搂垄脜脪 ( 脜脴猫脕鹿茅脫脢脪垄脪 )",
      "value": 34.621947
    },
    {
      "region_id": "2004",
      "region_name": "陇脜脥搂鹿脪路脟脮",
      "value": 38.080714
    },
    {
      "region_id": "2005",
      "region_name": "脌脪陇茫碌茅陆脩猫搂碌脨脟脩鹿脥脥隆碌脥鹿脜猫脪搂脢猫脟鹿路脮猫 1",
      "value": 38.487477
    },
    {
      "region_id": "2006",
      "region_name": "陇脜脥搂脿路戮脪",
      "value": 28.759501
    },
    {
      "region_id": "2101",
      "region_name": "脌脪陇茫碌茅陆脩猫搂碌脨脟脩鹿脥脥隆碌脥鹿脜猫脪搂脢猫脟鹿路脮猫 2",
      "value": 27.38906
    },
    {
      "region_id": "2102",
      "region_name": "谩脕猫鹿茅脫禄脩碌碌脪鹿脮碌脥鹿潞鹿",
      "value": 16.02882
    },
    {
      "region_id": "2103",
      "region_name": "谩脕猫鹿茅脫禄脩碌碌脪鹿脮碌脥鹿脜猫脪搂",
      "value": 24.814767
    },
    {
      "region_id": "2104",
      "region_name": "脌脪陇茫碌茅陆脩猫搂碌脨脟脩鹿脥脥隆碌脥鹿脜猫脪搂脢猫脟鹿路脮猫 3",
      "value": 29.952342
    },
    {
      "region_id": "2105",
      "region_name": "谩脕猫鹿茅脫脢脪脗潞脴脙脮",
      "value": 29.212018
    },
    {
      "region_id": "2106",
      "region_name": "谩脕猫鹿茅脫潞脪搂鹿脙脪",
      "value": 23.889282
    },
    {
      "region_id": "2107",
      "region_name": "谩脕猫鹿茅脫芒隆脜隆",
      "value": 25.076522
    },
    {
      "region_id": "2201",
      "region_name": "谩脕猫鹿茅脫隆脙脨潞脴脙脮 ( 脜脴猫脕鹿茅脫脢脪垄脪 )",
      "value": 74.315198
    },
    {
      "region_id": "2202",
      "region_name": "陇脜脥搂脜脨脥脴猫鹿",
      "value": 98.742538
    },
    {
      "region_id": "2203",
      "region_name": "脌脪陇茫碌茅陆脩猫搂碌脨脟脩鹿碌隆碌脥鹿潞鹿",
      "value": 179.32599
    },
    {
      "region_id": "2204",
      "region_name": "陇脜脥搂碌脨隆脩猫脟禄猫脪",
      "value": 192.10405
    },
    {
      "region_id": "2205",
      "region_name": "脌脪陇茫碌茅陆脩猫搂碌脨脟脩鹿碌隆脢猫脟鹿路脮猫 2",
      "value": 123.311485
    },
    {
      "region_id": "2206",
      "region_name": "脿隆脪脨脌脵脿隆莽碌",
      "value": 119.487316
    },
    {
      "region_id": "2207",
      "region_name": "陇脜脥搂路猫脥脕",
      "value": 63.814386
    },
    {
      "region_id": "2208",
      "region_name": "脌脪陇茫碌茅陆脩猫搂碌脨脟脩鹿碌隆脢猫脟鹿路脮猫 3",
      "value": 85.280124
    },
    {
      "region_id": "2209",
      "region_name": "谩脕猫鹿茅脫碌脙脩搂",
      "value": 54.243398
    },
    {
      "region_id": "2210",
      "region_name": "陇脜脥搂禄脨脿脣脜脮猫脗鹿",
      "value": 57.0349
    },
    {
      "region_id": "2211",
      "region_name": "陇脜脥搂脜脨搂脵",
      "value": 46.715949
    },
    {
      "region_id": "2212",
      "region_name": "陇脜脥搂潞脫潞脩搂",
      "value": 49.979818
    },
    {
      "region_id": "2213",
      "region_name": "脌脪陇茫碌茅陆脩猫搂碌脨脟脩鹿碌隆碌脥鹿脜猫脪搂",
      "value": 53.254124
    },
    {
      "region_id": "10-is",
      "region_name": "脿篓茅脪戮脙脨脗脪 (脿隆脪脨)",
      "value": 6.968238
    },
    {
      "region_id": "17-is",
      "region_name": "陋脪脗陆脩猫搂路脨脿脜碌脨脟脩鹿脥脥隆 (脿隆脪脨)",
      "value": 28.416251
    },
    {
      "region_id": "18-is",
      "region_name": "脿戮陋脙潞脴脙脮-禄脙脨篓脟潞陇脮脙脮垄脩鹿赂矛 (脿隆脪脨)",
      "value": 10.121091
    },
    {
      "region_id": "19-is",
      "region_name": "脌脪陇茫碌茅陆脩猫搂碌脨脟脩鹿脥脥隆碌脥鹿潞鹿 (脿隆脪脨)",
      "value": 4.673036
    },
    {
      "region_id": "20-is",
      "region_name": "路脨脿脜脢脪潞脢搂垄脜脪 (脿隆脪脨)",
      "value": null
    },
    {
      "region_id": "22-is",
      "region_name": "脌脪陇茫碌茅陆脩猫搂碌脨脟脩鹿碌隆 (脿隆脪脨)",
      "value": 99.716547
    }
  ]
}